{
	"configurations" : 
	[
		{
			"directories" : 
			[
				{
					"build" : ".",
					"childIndexes" : 
					[
						1
					],
					"hasInstallRule" : true,
					"minimumCMakeVersion" : 
					{
						"string" : "3.5"
					},
					"projectIndex" : 0,
					"source" : ".",
					"targetIndexes" : 
					[
						0,
						1,
						2,
						5
					]
				},
				{
					"build" : "gtest",
					"minimumCMakeVersion" : 
					{
						"string" : "3.8"
					},
					"parentIndex" : 0,
					"projectIndex" : 1,
					"source" : "/opt/ros/galactic/src/gtest_vendor",
					"targetIndexes" : 
					[
						3,
						4
					]
				}
			],
			"name" : "Release",
			"projects" : 
			[
				{
					"childIndexes" : 
					[
						1
					],
					"directoryIndexes" : 
					[
						0
					],
					"name" : "grid_map_core",
					"targetIndexes" : 
					[
						0,
						1,
						2,
						5
					]
				},
				{
					"directoryIndexes" : 
					[
						1
					],
					"name" : "gtest",
					"parentIndex" : 0,
					"targetIndexes" : 
					[
						3,
						4
					]
				}
			],
			"targets" : 
			[
				{
					"directoryIndex" : 0,
					"id" : "grid_map_core::@6890427a1f51a3e7e1df",
					"jsonFile" : "target-grid_map_core-Release-fbfc88e9a8160311f93a.json",
					"name" : "grid_map_core",
					"projectIndex" : 0
				},
				{
					"directoryIndex" : 0,
					"id" : "grid_map_core-test::@6890427a1f51a3e7e1df",
					"jsonFile" : "target-grid_map_core-test-Release-ef46478583c2394a646d.json",
					"name" : "grid_map_core-test",
					"projectIndex" : 0
				},
				{
					"directoryIndex" : 0,
					"id" : "grid_map_core_uninstall::@6890427a1f51a3e7e1df",
					"jsonFile" : "target-grid_map_core_uninstall-Release-fc7704554545339a826e.json",
					"name" : "grid_map_core_uninstall",
					"projectIndex" : 0
				},
				{
					"directoryIndex" : 1,
					"id" : "gtest::@0af4add9fe94340e763e",
					"jsonFile" : "target-gtest-Release-0c1553e2001bec0db46b.json",
					"name" : "gtest",
					"projectIndex" : 1
				},
				{
					"directoryIndex" : 1,
					"id" : "gtest_main::@0af4add9fe94340e763e",
					"jsonFile" : "target-gtest_main-Release-27109a72997689c27eb9.json",
					"name" : "gtest_main",
					"projectIndex" : 1
				},
				{
					"directoryIndex" : 0,
					"id" : "uninstall::@6890427a1f51a3e7e1df",
					"jsonFile" : "target-uninstall-Release-ba6510b0839df49639e3.json",
					"name" : "uninstall",
					"projectIndex" : 0
				}
			]
		}
	],
	"kind" : "codemodel",
	"paths" : 
	{
		"build" : "/home/sentry/Wolf-Moon/build/grid_map_core",
		"source" : "/home/sentry/Wolf-Moon/src/ThirdParty/grid_map/grid_map_core"
	},
	"version" : 
	{
		"major" : 2,
		"minor" : 0
	}
}
